[
  {
    "urn": "urn:cts:greekLit:tlg5026.msAint.hmt:6.200",
    "comment": "οτι ἀντι τοῦ ἐυ ναιομενην",
    "dse": {
      "urn": "urn:cite2:hmt:va_dse.v1:schol2707",
      "image_roi": "urn:cite2:hmt:vaimg.2017a:VA088VN_0591@0.84432572,0.42088520,0.04384672,0.01881051"
    },
    "references": [
      "urn:cts:greekLit:tlg0012.tlg001.msA-folios:88v.6.415"
    ]
  },
  {
    "urn": "urn:cts:greekLit:tlg5026.msAim.hmt:6.264",
    "comment": "Ἀρισταρχος δια του ο ναιετόωσαν",
    "dse": {
      "urn": "urn:cite2:hmt:va_dse.v1:schol2754",
      "image_roi": "urn:cite2:hmt:vaimg.2017a:VA088VN_0591@0.38946205,0.42918396,0.05526898,0.02240664"
    },
    "references": [
      "urn:cts:greekLit:tlg0012.tlg001.msA-folios:88v.6.415"
    ]
  },
  {
    "urn": "urn:cts:greekLit:tlg5026.msAim.hmt:6.265",
    "comment": "ἐσκύλευιε",
    "dse": {
      "urn": "urn:cite2:hmt:va_dse.v1:schol2755",
      "image_roi": "urn:cite2:hmt:vaimg.2017a:VA088VN_0591@0.39830508,0.46708160,0.04384672,0.01410788"
    },
    "references": [
      "urn:cts:greekLit:tlg0012.tlg001.msA-folios:88v.6.417"
    ]
  },
  {
    "urn": "urn:cts:greekLit:tlg5026.msAim.hmt:6.266",
    "comment": "καὶ τάφον ἔχωσαν",
    "dse": {
      "urn": "urn:cite2:hmt:va_dse.v1:schol2756",
      "image_roi": "urn:cite2:hmt:vaimg.2017a:VA088VN_0591@0.39204127,0.50525588,0.05268976,0.01410788"
    },
    "references": [
      "urn:cts:greekLit:tlg0012.tlg001.msA-folios:88v.6.419"
    ]
  },
  {
    "urn": "urn:cts:greekLit:tlg5026.msAim.hmt:6.267",
    "comment": "αἰφνιδίως ἐτελεύτησε τοῦς γραφεται αἱφνιδίως θανάτους ἀναφέρουσιν εἰς Ἀπολλωνα και Αρτεμιν ⁑",
    "dse": {
      "urn": "urn:cite2:hmt:va_dse.v1:schol2757",
      "image_roi": "urn:cite2:hmt:vaimg.2017a:VA088VN_0591@0.39646279,0.68008299,0.06411201,0.08271093"
    },
    "references": [
      "urn:cts:greekLit:tlg0012.tlg001.msA-folios:88v.6.428"
    ]
  }
]