[
  {
    "urn": "urn:cts:greekLit:tlg5026.msA.hmt:5.1006",
    "lemma": "‡ Δάρης ὡς Χάρης",
    "dse": {
      "urn": "urn:cite2:hmt:va_dse.v1:schol2275",
      "image_roi": "urn:cite2:hmt:vaimg.2017a:VA062VN_0564@0.19528371,0.12337483,0.65806927,0.08105118"
    },
    "references": [
      "urn:cts:greekLit:tlg0012.tlg001.msA-folios:62v.5.9"
    ],
    "comment": "ὁμολογεῖ καὶ ἡ γενικὴ Δάρητος γὰρ ὡς Χάρητος · εἰ γὰρ ὀξύνετο , ἡ γενικὴ ἐγίνετο Δαροῦς ὡς σαφοῦς , ὅτι τὰ εἰς ης δισύλλαβα ὀξύτονα ἓν ἔχοντας σύμφωνον εἰς ους περατοῦται κατὰ τὴν γενικήν σαφοῦς πρηνοῦς πρυλοὺς φραδοὺς φραδέος νόου ἔργα τοιαύτη ἄρα ἐγίνετο καὶ ἡ τοῦ προκειμένου ὀνόματος κλίσις περι δὲ τοῦ ψίλητος παρ' Αἰσχύλῳ , καὶ τοῦ Κουρῆτες τ' ἐμάχοντο . καὶ τοῦ κριτὴς ἐν τοῖς Περι ὀνομάτων ἀποδώσομεν τὸν λόγον· γέγονε δὲ τὸ Δάρης ἤτοι παρα το δείρω καὶ ἐκδείρω εοικὸς γὰρ ϊερεῖ . καὶ ἐχρήν γε αὐτῷ εἶναι Δέρης ὡς Φέρης , ἐτράπη  το ε εἰς α . ἠ παρα τὸ δαίω τὸ καίω ἐν πλεονασμῷ τοῦ ρ ⁑"
  },
  {
    "urn": "urn:cts:greekLit:tlg5026.msA.hmt:5.1007",
    "lemma": "ἢν δέ τις ἐν Τρώεσσι",
    "dse": {
      "urn": "urn:cite2:hmt:va_dse.v1:schol2276",
      "image_roi": "urn:cite2:hmt:vaimg.2017a:VA062VN_0564@0.20596905,0.18755187,0.64775239,0.03125864"
    },
    "references": [
      "urn:cts:greekLit:tlg0012.tlg001.msA-folios:62v.5.9"
    ],
    "comment": "τοῦτο τὸ εῖδος διήγησις λέγεται τρεῖς δὲ ἀρεται διηγήσεως σαφήνεια συντομία πιθανότης ἄπερ ἐνέθηκεν , τὸ ἔθνος τὸ ὄνομα τὴν τυχην · τὸν τρόπον τὴν ἀρχήν τῶν παίδων τὰ ὀνοματα καὶ τὴν ἀρετήν ‡"
  },
  {
    "urn": "urn:cts:greekLit:tlg5026.msA.hmt:5.1008",
    "lemma": "μεταμάζιον",
    "dse": {
      "urn": "urn:cite2:hmt:va_dse.v1:schol2277",
      "image_roi": "urn:cite2:hmt:vaimg.2017a:VA062VN_0564@0.19159912,0.21798064,0.20854827,0.09515906"
    },
    "references": [
      "urn:cts:greekLit:tlg0012.tlg001.msA-folios:62v.5.19"
    ],
    "comment": "οὕτως μεταμάζιον ἓν ποιητέον ὡς τὸ μεταφρενον καὶ ἐνωπιον παρῆκται δὲ παρα τὸ μαζός καὶ τὴν μετα ὡς παρα τὸ χθονός καὶ τὴν ἐπὶ ἐπιχθόνιος παρα ποταμὸν παραποτάμιος · γίνεται γὰρ καὶ ἀπο δύο λέξεων κατα παράθεσιν ἕν τι παραγωγον ὡς τὸ Νέαπολίτης καὶ ἄλλα μυρία ⁑"
  },
  {
    "urn": "urn:cts:greekLit:tlg5026.msA.hmt:5.1009",
    "lemma": "Ἱδαῖος δ’ ἀπόρουσε",
    "dse": {
      "urn": "urn:cite2:hmt:va_dse.v1:schol2278",
      "image_roi": "urn:cite2:hmt:vaimg.2017a:VA062VN_0564@0.18791452,0.31092669,0.22844510,0.21964039"
    },
    "references": [
      "urn:cts:greekLit:tlg0012.tlg001.msA-folios:62v.5.20"
    ],
    "comment": "κατηγορεῖ καὶ τούτου τοῦ τόπου ὁ Ζωΐλος ὅτι λίαν φησιν γελοίως πεποίηκεν ὁ ποιητης τὸν Ἰδαῖον ἀπολιπόντα τοὺς ἵππους καὶ τὸ ἅρμα φεύγειν ηδύνατο γὰρ μᾶλλον ἐπι τοῖς ἵπποις· ἀλλα ῥητέον ὅτι κατέθορε μὲν τοῦ άρματος , ὡς ὑπερασπίσων τὸν ἀδελφόν εὐλαβηθεὶς δὲ τὸν πολέμιον εἰς φυγὴν ἐτράπη· οἱ δὲ λεγουσιν ὅτι εἰδὼς τὸ Διομήδους φίλιππον δια τοῦτο εᾷ τοὺς ἵππους ὅπως περι αυτοὺς γένηται , ἠ ὅτι οὐκ ἔπεισε τῷ συμφέροντι αἱ γὰρ φρένες ταραχθῆσαι παρέπλαγξαν καὶ τὸ σοφόν τοιοῦτος εὑρίσκεται παρ αυτῷ καὶ ὁ Ἀλεξανδρος ἑλκόμενος ὑπο τοῦ ἐχθροῦ καὶ ἀγχόμενος ὑπο τῆς κόρυθος καὶ τῆς παρούσης συμφορᾶς καὶ ἀγνοῶν χρήσασθαι τῷ παρόντι ξίφει κατα τοῦ πολεμίου·"
  },
  {
    "urn": "urn:cts:greekLit:tlg5026.msA.hmt:5.1010",
    "lemma": "οὐδε γὰρ οὐδε κεν",
    "dse": {
      "urn": "urn:cite2:hmt:va_dse.v1:schol2279",
      "image_roi": "urn:cite2:hmt:vaimg.2017a:VA062VN_0564@0.19491525,0.52724758,0.22365512,0.04840941"
    },
    "references": [
      "urn:cts:greekLit:tlg0012.tlg001.msA-folios:62v.5.22"
    ],
    "comment": "ἡ μία περισσὴ ἀπόφα  οὐδε γὰρ οὐδε βίη οὐδε γὰρ οὐδε Δρύαντος , καὶ ἐστιν ἡ μία μὲν ἐπι τοῦ πραγματος θατέρα δὲ ἐπι τοῦ προσώπου ⁑"
  },
  {
    "urn": "urn:cts:greekLit:tlg5026.msA.hmt:5.1011",
    "lemma": "παρ όχεσφι",
    "dse": {
      "urn": "urn:cite2:hmt:va_dse.v1:schol2280",
      "image_roi": "urn:cite2:hmt:vaimg.2017a:VA062VN_0564@0.18349300,0.57372061,0.24465733,0.11701245"
    },
    "references": [
      "urn:cts:greekLit:tlg0012.tlg001.msA-folios:62v.5.28"
    ],
    "comment": "τὸ παρ όχεσφι , προσδιδόασι τινὲς τοῖς ἑξῆς ἵν ᾖ παρ' όχεσφι πᾶσιν ὀρίνθη θυμός , καὶ λέγει τοὺς ἁρματηλάτας τεταράχθαι , καὶ ἀλλαχοῦ ἱππηλασθαι φησὶν ἤδη τὰ ἅρματα· βέλτιον δὲ τοῖς ἄνω αὐτὸ προσδιδόναι καὶ νοεῖν ἐκ τοῦ παρ όχεσφιν τὸν τόπον τῶν ἁρμάτων , ἡ καὶ κυρίως , τὰ γὰρ ἅμα γινόμενα οὐ δυνατον ἅμα λέγεσθαι ⁑"
  },
  {
    "urn": "urn:cts:greekLit:tlg5026.msA.hmt:5.1013",
    "lemma": "τείχεσιπλῆτα",
    "dse": {
      "urn": "urn:cite2:hmt:va_dse.v1:schol2281",
      "image_roi": "urn:cite2:hmt:vaimg.2017a:VA062VN_0564@0.21075903,0.73471646,0.66249079,0.05255878"
    },
    "references": [
      "urn:cts:greekLit:tlg0012.tlg001.msA-folios:62v.5.31"
    ],
    "comment": "ὅτι Ζηνόδοτος γράφει τείχεσιβλῆτα ὁ τείχη καταβάλλων· Ποσειδῶνος δὲ ἔργον τὸ ἐκ θεμελίων καταβάλλειν καὶ τὰ ἐπίγεια σείειν , Ἄρεος δὲ τοῖς τείχεσι προσπελάζειν· καὶ ἔστιν ἐπιθετον ἀνάλογον τὸ παρὰ Στησιχώρῳ · πυλεμάχῳ ⁑"
  }
]